hawat
mentat
vial
