Metadata-Version: 2.1
Name: mentat-ng
Version: 2.7.4
Summary: Distributed modular SIEM system designed to monitor networks of all sizes
Home-page: https://homeproj.cesnet.cz/git/mentat-ng.git
Author: CESNET-CERTS Development Team
Author-email: csirt@cesnet.cz
License: MIT
Keywords: library
Platform: UNKNOWN
Classifier: Development Status :: 4 - Beta
Classifier: License :: OSI Approved :: MIT License
Classifier: Programming Language :: Python :: 3 :: Only
Provides-Extra: dev
